fasthep/__init__.py
fasthep/py.typed
fasthep-0.1.0.dist-info/LICENSE
fasthep-0.1.0.dist-info/WHEEL
fasthep-0.1.0.dist-info/METADATA
fasthep-0.1.0.dist-info/RECORD
