Metadata-Version: 2.1
Name: fasthep
Version: 0.1.0
Summary: A meta package for the FAST-HEP toolkit
Author-email: Luke Kreczko <fast-hep@cern.ch>
Requires-Python: >=3.7
Classifier: Development Status :: 1 - Planning
Classifier: Intended Audience :: Science/Research
Classifier: Intended Audience :: Developers
Classifier: License :: OSI Approved :: Apache Software License
Classifier: Operating System :: OS Independent
Classifier: Programming Language :: Python
Classifier: Programming Language :: Python :: 3
Classifier: Programming Language :: Python :: 3 :: Only
Classifier: Programming Language :: Python :: 3.7
Classifier: Programming Language :: Python :: 3.8
Classifier: Programming Language :: Python :: 3.9
Classifier: Programming Language :: Python :: 3.10
Classifier: Topic :: Scientific/Engineering
Classifier: Typing :: Typed
Requires-Dist: fasthep-cli
Requires-Dist: fasthep-logging
Requires-Dist: typing_extensions >=3.7; python_version<'3.8'
Requires-Dist: fast-carpenter ; extra == "carpenter"
Requires-Dist: fast-curator ; extra == "carpenter"
Requires-Dist: fast-flow ; extra == "carpenter"
Requires-Dist: pytest >=6 ; extra == "dev"
Requires-Dist: pytest-cov >=3 ; extra == "dev"
Requires-Dist: pre-commit ; extra == "dev"
Requires-Dist: mypy >=0.971 ; extra == "dev"
Requires-Dist: Sphinx>=4.0 ; extra == "docs"
Requires-Dist: myst_parser>=0.13 ; extra == "docs"
Requires-Dist: sphinx-book-theme>=0.1.0 ; extra == "docs"
Requires-Dist: sphinx_copybutton ; extra == "docs"
Requires-Dist: fast-carpenter ; extra == "full"
Requires-Dist: fast-curator ; extra == "full"
Requires-Dist: fast-flow ; extra == "full"
Requires-Dist: fast-plotter ; extra == "full"
Requires-Dist: scikit-validate ; extra == "full"
Requires-Dist: fast-plotter ; extra == "plot"
Requires-Dist: pytest >=6 ; extra == "test"
Requires-Dist: pytest-cov >=3 ; extra == "test"
Requires-Dist: scikit-validate ; extra == "validate"
Project-URL: Bug Tracker, https://github.com/FAST-HEP/fasthep/issues
Project-URL: Changelog, https://github.com/FAST-HEP/fasthep/releases
Project-URL: Discussions, https://github.com/FAST-HEP/fasthep/discussions
Project-URL: Homepage, https://github.com/FAST-HEP/fasthep
Provides-Extra: carpenter
Provides-Extra: dev
Provides-Extra: docs
Provides-Extra: full
Provides-Extra: plot
Provides-Extra: test
Provides-Extra: validate
